setup.py
egen111222_auth_util_123123.egg-info/PKG-INFO
egen111222_auth_util_123123.egg-info/SOURCES.txt
egen111222_auth_util_123123.egg-info/dependency_links.txt
egen111222_auth_util_123123.egg-info/top_level.txt
project/main.py