Metadata-Version: 2.1
Name: egen111222-auth-util-123123
Version: 1.0
Summary: Система аутентифікації
Author: Kirill
Author-email: 123@gmail.com
